<?xml version="1.0" ?>
<annotation>
 <folder>widerface</folder>
 <filename>000005.jpg</filename>
 <source>
  <database>wider face Database</database>
  <annotation>PASCAL VOC2007</annotation>
  <flikerid>-1</flikerid>
 </source>
 <size>
  <width>500</width>
  <height>375</height>
  <depth>3</depth>
 </size>
 <segmented>0</segmented>
 <object>
  <name>chair</name>
  <pose>Unspecified</pose>
  <truncated>1</truncated>
  <difficult>0</difficult>
  <bndbox>
   <xmin>263.0</xmin>
   <ymin>211.0</ymin>
   <xmax>324.0</xmax>
   <ymax>339.0</ymax>
  </bndbox>
 </object>
 <object>
  <name>chair</name>
  <pose>Unspecified</pose>
  <truncated>1</truncated>
  <difficult>0</difficult>
  <bndbox>
   <xmin>165.0</xmin>
   <ymin>264.0</ymin>
   <xmax>253.0</xmax>
   <ymax>372.0</ymax>
  </bndbox>
 </object>
 <object>
  <name>chair</name>
  <pose>Unspecified</pose>
  <truncated>1</truncated>
  <difficult>0</difficult>
  <bndbox>
   <xmin>5.0</xmin>
   <ymin>244.0</ymin>
   <xmax>67.0</xmax>
   <ymax>374.0</ymax>
  </bndbox>
 </object>
 <object>
  <name>chair</name>
  <pose>Unspecified</pose>
  <truncated>1</truncated>
  <difficult>0</difficult>
  <bndbox>
   <xmin>241.0</xmin>
   <ymin>194.0</ymin>
   <xmax>295.0</xmax>
   <ymax>299.0</ymax>
  </bndbox>
 </object>
 <object>
  <name>chair</name>
  <pose>Unspecified</pose>
  <truncated>1</truncated>
  <difficult>0</difficult>
  <bndbox>
   <xmin>277.0</xmin>
   <ymin>186.0</ymin>
   <xmax>312.0</xmax>
   <ymax>220.0</ymax>
  </bndbox>
 </object>
</annotation>
